{"trial_id": "006", "hyperparameters": {"space": [{"class_name": "Int", "config": {"name": "units", "default": null, "conditions": [], "min_value": 10, "max_value": 30, "step": 2, "sampling": "linear"}}, {"class_name": "Choice", "config": {"name": "momentum", "default": 0.9, "conditions": [], "values": [0.9, 0.7, 0.5, 0.3], "ordered": true}}], "values": {"units": 26, "momentum": 0.7}}, "metrics": {"metrics": {"loss": {"direction": "min", "observations": [{"value": [2.3938523133595786], "step": 97}]}}}, "score": 2.3938523133595786, "best_step": 97, "status": "COMPLETED", "message": null}